{
  "intents": [
    {
      "intent": "Greeting",
      "examples": [
        {
          "text": "Good Afternoon"
        },
        {
          "text": "Good Evening"
        },
        {
          "text": "Good Morning"
        },
        {
          "text": "Hello"
        },
        {
          "text": "Hi"
        }
      ],
      "description": ""
    },
    {
      "intent": "QandA",
      "examples": [
        {
          "text": "Can you suggest me a place to travel in India"
        },
        {
          "text": "I want to travel within India"
        },
        {
          "text": "show me more"
        },
        {
          "text": "what else"
        },
        {
          "text": "Which part of India should I travel to"
        }
      ],
      "description": ""
    },
    {
      "intent": "visit",
      "examples": [
        {
          "text": "Can you please suggest me a place in India"
        },
        {
          "text": "I want to travel"
        },
        {
          "text": "I want to visit a place in India"
        },
        {
          "text": "show me more"
        },
        {
          "text": "what else"
        }
      ],
      "description": ""
    }
  ],
  "entities": [
    {
      "entity": "cultureN",
      "values": [
        {
          "type": "synonyms",
          "value": "culture",
          "synonyms": []
        }
      ],
      "fuzzy_match": true
    },
    {
      "entity": "cultureS",
      "values": [
        {
          "type": "synonyms",
          "value": "culture",
          "synonyms": []
        }
      ],
      "fuzzy_match": true
    },
    {
      "entity": "directions",
      "values": [
        {
          "type": "synonyms",
          "value": "North India",
          "synonyms": [
            "north"
          ]
        },
        {
          "type": "synonyms",
          "value": "South India",
          "synonyms": [
            "south"
          ]
        }
      ],
      "fuzzy_match": true
    },
    {
      "entity": "email",
      "values": [
        {
          "type": "patterns",
          "value": "email",
          "patterns": [
            "\\b[A-Za-z0-9._%+-]+@([A-Za-z0-9-]+\\.)+[A-Za-z]{2,}\\b"
          ]
        }
      ],
      "fuzzy_match": true
    },
    {
      "entity": "foodN",
      "values": [
        {
          "type": "synonyms",
          "value": "food",
          "synonyms": []
        }
      ],
      "fuzzy_match": true
    },
    {
      "entity": "foodS",
      "values": [
        {
          "type": "synonyms",
          "value": "food",
          "synonyms": []
        }
      ],
      "fuzzy_match": true
    },
    {
      "entity": "greetings",
      "values": [
        {
          "type": "synonyms",
          "value": "Good Afternoon",
          "synonyms": [
            "ga",
            "gud evng"
          ]
        },
        {
          "type": "synonyms",
          "value": "Good Evening",
          "synonyms": [
            "ge",
            "gud aftn"
          ]
        },
        {
          "type": "synonyms",
          "value": "Good Morning",
          "synonyms": [
            "gm",
            "gud mrng"
          ]
        }
      ],
      "fuzzy_match": true
    },
    {
      "entity": "loc",
      "values": [
        {
          "type": "synonyms",
          "value": "Amritsar, Punjab",
          "synonyms": []
        },
        {
          "type": "synonyms",
          "value": "Delhi",
          "synonyms": []
        },
        {
          "type": "synonyms",
          "value": "Hampi, Karnataka",
          "synonyms": [
            "hampi"
          ]
        },
        {
          "type": "synonyms",
          "value": "Jaipur, Rajasthan",
          "synonyms": [
            "jaipur"
          ]
        },
        {
          "type": "synonyms",
          "value": "Kerala Backwaters",
          "synonyms": []
        },
        {
          "type": "synonyms",
          "value": "Madurai, Tamil Nadu",
          "synonyms": []
        },
        {
          "type": "synonyms",
          "value": "Ooty, Tamil Nadu",
          "synonyms": []
        },
        {
          "type": "synonyms",
          "value": "Pondicherry (Puducherry)",
          "synonyms": []
        },
        {
          "type": "synonyms",
          "value": "Taj Mahal, Uttar Pradesh",
          "synonyms": []
        },
        {
          "type": "synonyms",
          "value": "Varanasi, Uttar Pradesh",
          "synonyms": []
        }
      ],
      "fuzzy_match": true
    },
    {
      "entity": "mode",
      "values": [
        {
          "type": "synonyms",
          "value": "plane",
          "synonyms": [
            "aeroplane",
            "flight"
          ]
        },
        {
          "type": "synonyms",
          "value": "road",
          "synonyms": [
            "bus",
            "car",
            "SUV",
            "tempo"
          ]
        },
        {
          "type": "synonyms",
          "value": "train",
          "synonyms": [
            "rail",
            "railway"
          ]
        }
      ],
      "fuzzy_match": true
    },
    {
      "entity": "num",
      "values": [
        {
          "type": "synonyms",
          "value": "1",
          "synonyms": [
            "good"
          ]
        },
        {
          "type": "synonyms",
          "value": "2",
          "synonyms": [
            "better"
          ]
        },
        {
          "type": "synonyms",
          "value": "3",
          "synonyms": [
            "best"
          ]
        }
      ],
      "fuzzy_match": true
    },
    {
      "entity": "QandA",
      "values": [
        {
          "type": "synonyms",
          "value": "location",
          "synonyms": [
            "places",
            "spot",
            "travel"
          ]
        }
      ],
      "fuzzy_match": true
    },
    {
      "entity": "sys-date",
      "values": [],
      "fuzzy_match": true
    },
    {
      "entity": "sys-number",
      "values": [],
      "fuzzy_match": true
    },
    {
      "entity": "sys-time",
      "values": [],
      "fuzzy_match": true
    },
    {
      "entity": "thanking",
      "values": [
        {
          "type": "synonyms",
          "value": "thanks",
          "synonyms": [
            "k",
            "kk",
            "ok",
            "okay",
            "thanks",
            "thank you"
          ]
        }
      ],
      "fuzzy_match": true
    },
    {
      "entity": "touristspotN",
      "values": [
        {
          "type": "synonyms",
          "value": "tourist spot",
          "synonyms": []
        }
      ],
      "fuzzy_match": true
    },
    {
      "entity": "touristspotS",
      "values": [
        {
          "type": "synonyms",
          "value": "tourist spot",
          "synonyms": []
        }
      ],
      "fuzzy_match": true
    },
    {
      "entity": "visit",
      "values": [
        {
          "type": "synonyms",
          "value": "visit",
          "synonyms": [
            "go",
            "see",
            "travel",
            "view",
            "yes"
          ]
        }
      ],
      "fuzzy_match": true
    }
  ],
  "metadata": {
    "api_version": {
      "major_version": "v2",
      "minor_version": "2018-11-08"
    }
  },
  "dialog_nodes": [
    {
      "type": "standard",
      "title": "Anything else",
      "output": {
        "generic": [
          {
            "values": [
              {
                "text": "I didn't understand. You can try rephrasing."
              },
              {
                "text": "Can you reword your statement? I'm not understanding."
              },
              {
                "text": "I didn't get your meaning."
              }
            ],
            "response_type": "text",
            "selection_policy": "sequential"
          }
        ]
      },
      "conditions": "anything_else",
      "dialog_node": "Anything else",
      "previous_sibling": "node_9_1617986737153",
      "disambiguation_opt_out": true
    },
    {
      "type": "event_handler",
      "output": {
        "text": {
          "values": [
            "Where do you want to visit?"
          ],
          "selection_policy": "sequential"
        }
      },
      "parent": "slot_1_1618029207044",
      "event_name": "focus",
      "dialog_node": "handler_10_1618029207046",
      "previous_sibling": "handler_8_1618029207045"
    },
    {
      "type": "event_handler",
      "output": {
        "generic": []
      },
      "parent": "node_8_1617950358321",
      "event_name": "focus",
      "dialog_node": "handler_1_1617950708040",
      "previous_sibling": "node_9_1617951626721"
    },
    {
      "type": "event_handler",
      "output": {
        "text": {
          "values": [
            "Enter place"
          ],
          "selection_policy": "sequential"
        }
      },
      "parent": "slot_2_1618032195295",
      "event_name": "focus",
      "dialog_node": "handler_2_1618032195296",
      "previous_sibling": "handler_3_1618032195296"
    },
    {
      "type": "event_handler",
      "output": {},
      "parent": "slot_2_1618032195295",
      "context": {
        "loc": "@loc"
      },
      "conditions": "@loc",
      "event_name": "input",
      "dialog_node": "handler_3_1618032195296"
    },
    {
      "type": "event_handler",
      "output": {
        "text": {
          "values": [
            "How many members are travelling?"
          ],
          "selection_policy": "sequential"
        }
      },
      "parent": "slot_4_1618029273274",
      "event_name": "focus",
      "dialog_node": "handler_4_1618029273275",
      "previous_sibling": "handler_6_1618029273275"
    },
    {
      "type": "event_handler",
      "output": {},
      "parent": "slot_8_1618029483914",
      "context": {
        "number_2": "@sys-number"
      },
      "conditions": "@sys-number",
      "event_name": "input",
      "dialog_node": "handler_4_1618029483915"
    },
    {
      "type": "event_handler",
      "output": {},
      "parent": "slot_10_1618031684160",
      "context": {
        "mode": "@mode"
      },
      "conditions": "@mode",
      "event_name": "input",
      "dialog_node": "handler_5_1618031684162"
    },
    {
      "type": "event_handler",
      "output": {},
      "parent": "slot_4_1618029273274",
      "context": {
        "number": "@sys-number"
      },
      "conditions": "@sys-number",
      "event_name": "input",
      "dialog_node": "handler_6_1618029273275"
    },
    {
      "type": "event_handler",
      "output": {
        "text": {
          "values": [
            "Date of departure"
          ],
          "selection_policy": "sequential"
        }
      },
      "parent": "slot_10_1618029341112",
      "event_name": "focus",
      "dialog_node": "handler_6_1618029341113",
      "previous_sibling": "handler_9_1618029341113"
    },
    {
      "type": "event_handler",
      "output": {
        "text": {
          "values": [
            "How many days are you travelling?"
          ],
          "selection_policy": "sequential"
        }
      },
      "parent": "slot_8_1618029483914",
      "event_name": "focus",
      "dialog_node": "handler_7_1618029483915",
      "previous_sibling": "handler_4_1618029483915"
    },
    {
      "type": "event_handler",
      "output": {},
      "parent": "slot_1_1618029207044",
      "context": {
        "visit_visit": "@visit:visit"
      },
      "conditions": "@visit:visit",
      "event_name": "input",
      "dialog_node": "handler_8_1618029207045"
    },
    {
      "type": "event_handler",
      "output": {},
      "parent": "slot_10_1618029341112",
      "context": {
        "date": "@sys-date"
      },
      "conditions": "@sys-date",
      "event_name": "input",
      "dialog_node": "handler_9_1618029341113"
    },
    {
      "type": "event_handler",
      "output": {
        "text": {
          "values": [
            "Enter mode of transport"
          ],
          "selection_policy": "sequential"
        }
      },
      "parent": "slot_10_1618031684160",
      "event_name": "focus",
      "dialog_node": "handler_9_1618031684162",
      "previous_sibling": "handler_5_1618031684162"
    },
    {
      "type": "standard",
      "title": "email",
      "output": {
        "generic": [
          {
            "values": [
              {
                "text": "Thank you for giving your email ID. your mail id $email is used for further reference.\nHow can I help you?"
              }
            ],
            "response_type": "text",
            "selection_policy": "sequential"
          }
        ]
      },
      "parent": "Welcome",
      "context": {
        "email": "@email.literal"
      },
      "conditions": "@email",
      "dialog_node": "node_1_1617952731242"
    },
    {
      "type": "standard",
      "title": "culture",
      "output": {
        "generic": [
          {
            "source": "https://www.tripsavvy.com/thmb/-tfYbjT-9QeDtd32UbF8p8Arl9E=/2122x1415/filters:fill(auto,1)/GettyImages-157455052-56a87ea73df78cf7729e572c.jpg",
            "response_type": "image"
          },
          {
            "values": [
              {
                "text": "South Indian women traditionally wear the sari while the men wear a type of sarong, which could be either a white dhoti or a colourful lungi with typical batik patterns. The South Indian culture is celebrated in the elaborate dance forms of South India: Koodiyattam, Bharatanatyam, Oyilattam, Karakattam, Kuchipudi, Kathakali, Thirayattam,[27] Theyyam, Bhuta Kola, Ottamthullal, Oppana, Kerala Natanam, Mohiniaattam and Yakshagana."
              }
            ],
            "response_type": "text",
            "selection_policy": "sequential"
          }
        ]
      },
      "parent": "node_6_1617982502199",
      "conditions": "@cultureS:culture",
      "dialog_node": "node_1_1617983432145",
      "previous_sibling": "node_6_1617982925620"
    },
    {
      "type": "standard",
      "title": "culture",
      "output": {
        "generic": [
          {
            "source": "https://tse1.mm.bing.net/th?id=OIP.xT4kQyEcYMHAFmtIVSc8hgHaEq&pid=Api&P=0&w=256&h=162",
            "response_type": "image"
          },
          {
            "values": [
              {
                "text": "Women traditionally wear salwar kameez, gagra choli, sari and phiran. Dupatta is worn to complete the outfit. Men traditionally wear kurta, achkan, kameez and sherwani for upper garment, lower garment includes dhoti, churidar, shalwar and Lungi. The rich cultural diversity of North India is most clearly shown by the many different folk dance styles found here. Starting with Bhangra (men’s dance) and Giddha (women’s dance) from Punjab to Kathak in Uttar Pradesh; from Ghoomar and Kalbeliya dance from Rajasthan to Nati from Himachal Pradesh; Karma from Jharkhand to Panthi from Chhattisgarh; from Jagars and Pandva Nritya from Uttarakhand to Rouf of Kashmir celebrates the richness of culture and traditions of North India."
              }
            ],
            "response_type": "text",
            "selection_policy": "sequential"
          }
        ]
      },
      "parent": "node_8_1617982759591",
      "conditions": "@cultureN:culture",
      "dialog_node": "node_1_1617984736871",
      "previous_sibling": "node_3_1617984507564"
    },
    {
      "type": "standard",
      "title": "thanking",
      "output": {
        "generic": [
          {
            "values": [
              {
                "text": "I hope you liked it."
              }
            ],
            "response_type": "text",
            "selection_policy": "sequential"
          },
          {
            "values": [
              {
                "text": "Can you please rate the service \n1 for Good , 2 for Better and 3 for Best"
              }
            ],
            "response_type": "text",
            "selection_policy": "sequential"
          }
        ]
      },
      "conditions": "@thanking:thanks",
      "dialog_node": "node_2_1617985871538",
      "previous_sibling": "node_8_1617950358321"
    },
    {
      "type": "standard",
      "title": "food",
      "output": {
        "generic": [
          {
            "source": "https://s-media-cache-ak0.pinimg.com/736x/22/0e/2c/220e2cb270e24151c2b3e2f55d999d5b.jpg",
            "response_type": "image"
          },
          {
            "source": "https://b.zmtcdn.com/data/menus/559/16566559/9a7a3f5a52b4390aa0c36d90ac342b61.jpg",
            "response_type": "image"
          }
        ]
      },
      "parent": "node_8_1617982759591",
      "conditions": "@foodN:food",
      "dialog_node": "node_3_1617984507564"
    },
    {
      "type": "standard",
      "title": "tourist spot",
      "output": {
        "generic": [
          {
            "source": "https://www.visittnt.com/blog/wp-content/uploads/2018/11/North-India.jpg",
            "response_type": "image"
          },
          {
            "title": "tourist spots",
            "options": [
              {
                "label": "Delhi ",
                "value": {
                  "input": {
                    "text": "Delhi "
                  }
                }
              },
              {
                "label": " Taj Mahal, Uttar Pradesh ",
                "value": {
                  "input": {
                    "text": "Taj Mahal, Uttar Pradesh "
                  }
                }
              },
              {
                "label": "Jaipur, Rajasthan ",
                "value": {
                  "input": {
                    "text": "Jaipur, Rajasthan "
                  }
                }
              },
              {
                "label": "Amritsar, Punjab",
                "value": {
                  "input": {
                    "text": "Amritsar, Punjab"
                  }
                }
              },
              {
                "label": "Varanasi, Uttar Pradesh",
                "value": {
                  "input": {
                    "text": "Varanasi, Uttar Pradesh"
                  }
                }
              }
            ],
            "response_type": "option"
          },
          {
            "values": [
              {
                "text": "Do you want to visit?"
              }
            ],
            "response_type": "text",
            "selection_policy": "sequential"
          }
        ]
      },
      "parent": "node_8_1617982759591",
      "conditions": "@touristspotN:(tourist spot)",
      "dialog_node": "node_4_1617984964225",
      "previous_sibling": "node_1_1617984736871"
    },
    {
      "type": "standard",
      "title": "part",
      "output": {
        "generic": [
          {
            "title": "South India specialties ",
            "options": [
              {
                "label": "food",
                "value": {
                  "input": {
                    "text": "food"
                  }
                }
              },
              {
                "label": "culture",
                "value": {
                  "input": {
                    "text": "culture"
                  }
                }
              },
              {
                "label": "tourist spot",
                "value": {
                  "input": {
                    "text": "tourist spot"
                  }
                }
              }
            ],
            "response_type": "option"
          }
        ]
      },
      "parent": "node_7_1617948369372",
      "conditions": "@directions:(South India)",
      "dialog_node": "node_6_1617982502199"
    },
    {
      "type": "standard",
      "title": "food",
      "output": {
        "generic": [
          {
            "source": "https://qph.fs.quoracdn.net/main-qimg-487e12d2c8eb8337903082e6d083ef41",
            "response_type": "image"
          },
          {
            "source": "https://d6ozfheqtj1tz.cloudfront.net/ChIJL7qMqOp954gR41neRkPSwj4/5d886361b36ed.jpg",
            "response_type": "image"
          }
        ]
      },
      "parent": "node_6_1617982502199",
      "conditions": "@foodS:food",
      "dialog_node": "node_6_1617982925620"
    },
    {
      "type": "standard",
      "title": "tourist spot",
      "output": {
        "generic": [
          {
            "source": "https://tse4.mm.bing.net/th?id=OIP.yuxjt9wfOA0-rcpPm_hnLwHaE8&pid=Api&P=0&w=249&h=166",
            "response_type": "image"
          },
          {
            "title": "tourist spots",
            "options": [
              {
                "label": "Hampi, Karnataka ",
                "value": {
                  "input": {
                    "text": "Hampi, Karnataka "
                  }
                }
              },
              {
                "label": "Kerala Backwaters ",
                "value": {
                  "input": {
                    "text": "Kerala Backwaters "
                  }
                }
              },
              {
                "label": "Madurai, Tamil Nadu ",
                "value": {
                  "input": {
                    "text": "Madurai, Tamil Nadu "
                  }
                }
              },
              {
                "label": "Pondicherry (Puducherry)",
                "value": {
                  "input": {
                    "text": "Pondicherry (Puducherry)"
                  }
                }
              },
              {
                "label": "Ooty, Tamil Nadu",
                "value": {
                  "input": {
                    "text": "Ooty, Tamil Nadu"
                  }
                }
              }
            ],
            "response_type": "option"
          },
          {
            "values": [
              {
                "text": "Do you want to visit?"
              }
            ],
            "response_type": "text",
            "selection_policy": "sequential"
          }
        ]
      },
      "parent": "node_6_1617982502199",
      "conditions": "@touristspotS:(tourist spot)",
      "dialog_node": "node_6_1617984004516",
      "previous_sibling": "node_1_1617983432145"
    },
    {
      "type": "standard",
      "title": "QandA",
      "metadata": {
        "_customization": {
          "mcr": true
        }
      },
      "conditions": "#QandA || @QandA",
      "dialog_node": "node_7_1617948369372",
      "previous_sibling": "node_8_1617946927082"
    },
    {
      "type": "standard",
      "title": "Greetings",
      "metadata": {
        "_customization": {
          "mcr": true
        }
      },
      "conditions": "#Greeting || @greetings",
      "dialog_node": "node_8_1617946927082",
      "previous_sibling": "Welcome"
    },
    {
      "type": "frame",
      "title": "Visit",
      "output": {
        "generic": [
          {
            "values": [
              {
                "text": "Your plan of $number_2 days starting on $date to $loc is acknowledged.\nThe total amount and other details are sent to $email."
              }
            ],
            "response_type": "text",
            "selection_policy": "sequential"
          }
        ]
      },
      "metadata": {
        "_customization": {
          "mcr": false
        }
      },
      "next_step": {
        "behavior": "skip_user_input"
      },
      "conditions": "#visit || @visit",
      "dialog_node": "node_8_1617950358321",
      "previous_sibling": "node_7_1617948369372"
    },
    {
      "type": "standard",
      "title": "part",
      "output": {
        "generic": [
          {
            "title": "North India specialties ",
            "options": [
              {
                "label": "food",
                "value": {
                  "input": {
                    "text": "food"
                  }
                }
              },
              {
                "label": "culture",
                "value": {
                  "input": {
                    "text": "culture"
                  }
                }
              },
              {
                "label": "tourist spot",
                "value": {
                  "input": {
                    "text": "tourist spot"
                  }
                }
              }
            ],
            "response_type": "option"
          }
        ]
      },
      "parent": "node_7_1617948369372",
      "conditions": "@directions:(North India)",
      "dialog_node": "node_8_1617982759591",
      "previous_sibling": "node_6_1617982502199"
    },
    {
      "type": "standard",
      "title": "Deleting Context",
      "output": {
        "deleted": "<?context.remove('visit_visit')?><?context.remove('number')?><?context.remove('date')?><?context.remove('number_2')?><?context.remove('mode')?><?context.remove('loc')?>",
        "generic": [
          {
            "values": [],
            "response_type": "text",
            "selection_policy": "sequential"
          }
        ]
      },
      "parent": "node_8_1617950358321",
      "conditions": "true",
      "dialog_node": "node_9_1617951626721",
      "previous_sibling": "response_3_1617980750406"
    },
    {
      "type": "standard",
      "title": "end",
      "output": {
        "generic": [
          {
            "values": [
              {
                "text": "Thank You !Come again. "
              }
            ],
            "response_type": "text",
            "selection_policy": "sequential"
          }
        ]
      },
      "conditions": "@num",
      "dialog_node": "node_9_1617986737153",
      "previous_sibling": "node_2_1617985871538"
    },
    {
      "type": "response_condition",
      "output": {
        "generic": [
          {
            "values": [
              {
                "text": "Good Evening!! How can I help you ?"
              }
            ],
            "response_type": "text",
            "selection_policy": "sequential"
          }
        ]
      },
      "parent": "node_8_1617946927082",
      "conditions": "@greetings:(Good Evening)",
      "dialog_node": "response_1_1617947523404",
      "previous_sibling": "response_5_1617947383181"
    },
    {
      "type": "response_condition",
      "output": {
        "generic": [
          {
            "values": [
              {
                "text": "Good Afternoon!! How can I help you ?"
              }
            ],
            "response_type": "text",
            "selection_policy": "sequential"
          }
        ]
      },
      "parent": "node_8_1617946927082",
      "conditions": "@greetings:(Good Afternoon)",
      "dialog_node": "response_3_1617947548544",
      "previous_sibling": "response_1_1617947523404"
    },
    {
      "type": "response_condition",
      "output": {
        "generic": [
          {
            "values": [
              {
                "text": "Thank you, your order of $number plates of $items is placed. Please pay using $payment . your receipt is sent to $email"
              }
            ],
            "response_type": "text",
            "selection_policy": "sequential"
          }
        ]
      },
      "parent": "node_8_1617950358321",
      "disabled": true,
      "dialog_node": "response_3_1617980750406",
      "previous_sibling": "slot_2_1618032195295"
    },
    {
      "type": "response_condition",
      "output": {
        "generic": [
          {
            "values": [
              {
                "text": "Good Morning!! How can I help you ?"
              }
            ],
            "response_type": "text",
            "selection_policy": "sequential"
          }
        ]
      },
      "parent": "node_8_1617946927082",
      "conditions": "@greetings:(Good Morning)",
      "dialog_node": "response_5_1617947383181"
    },
    {
      "type": "response_condition",
      "output": {
        "generic": [
          {
            "title": "Sure, which part of India",
            "options": [
              {
                "label": "North India",
                "value": {
                  "input": {
                    "text": "North India"
                  }
                }
              },
              {
                "label": "South India",
                "value": {
                  "input": {
                    "text": "South India"
                  }
                }
              }
            ],
            "response_type": "option"
          }
        ]
      },
      "parent": "node_7_1617948369372",
      "conditions": "@QandA:location",
      "dialog_node": "response_8_1617948539941",
      "previous_sibling": "node_8_1617982759591"
    },
    {
      "type": "slot",
      "parent": "node_8_1617950358321",
      "variable": "$date",
      "dialog_node": "slot_10_1618029341112",
      "previous_sibling": "slot_4_1618029273274"
    },
    {
      "type": "slot",
      "parent": "node_8_1617950358321",
      "variable": "$mode",
      "dialog_node": "slot_10_1618031684160",
      "previous_sibling": "slot_8_1618029483914"
    },
    {
      "type": "slot",
      "parent": "node_8_1617950358321",
      "variable": "$visit_visit",
      "dialog_node": "slot_1_1618029207044"
    },
    {
      "type": "slot",
      "parent": "node_8_1617950358321",
      "variable": "$loc",
      "dialog_node": "slot_2_1618032195295",
      "previous_sibling": "slot_10_1618031684160"
    },
    {
      "type": "slot",
      "parent": "node_8_1617950358321",
      "variable": "$number",
      "dialog_node": "slot_4_1618029273274",
      "previous_sibling": "slot_1_1618029207044"
    },
    {
      "type": "slot",
      "parent": "node_8_1617950358321",
      "variable": "$number_2",
      "dialog_node": "slot_8_1618029483914",
      "previous_sibling": "slot_10_1618029341112"
    },
    {
      "type": "standard",
      "title": "Welcome",
      "output": {
        "generic": [
          {
            "values": [
              {
                "text": "Hello, I am Eagle bot, How can I help you, please provide your email ID ?"
              }
            ],
            "response_type": "text",
            "selection_policy": "sequential"
          }
        ]
      },
      "conditions": "welcome",
      "dialog_node": "Welcome"
    }
  ],
  "counterexamples": [],
  "system_settings": {
    "off_topic": {
      "enabled": true
    },
    "disambiguation": {
      "prompt": "Did you mean:",
      "enabled": true,
      "randomize": true,
      "max_suggestions": 5,
      "suggestion_text_policy": "title",
      "none_of_the_above_prompt": "None of the above"
    },
    "system_entities": {
      "enabled": true
    },
    "human_agent_assist": {
      "prompt": "Did you mean:"
    },
    "intent_classification": {
      "training_backend_version": "v2"
    },
    "spelling_auto_correct": true
  },
  "learning_opt_out": false,
  "name": "Eagle Bot",
  "language": "en",
  "description": ""
}